pysonarr/__init__.py
pysonarr/backup.py
pysonarr/client.py
pysonarr/enums/__init__.py
pysonarr/enums/backup_resource.py
pysonarr/schemas/__init__.py
pysonarr/schemas/backup_resource.py
pysonarr-0.1.0.dist-info/METADATA
pysonarr-0.1.0.dist-info/WHEEL
pysonarr-0.1.0.dist-info/licenses/LICENSE
pysonarr-0.1.0.dist-info/RECORD
